gaitmap_challenges/__init__.py
gaitmap_challenges/_utils.py
gaitmap_challenges/challenge_base.py
gaitmap_challenges/config.py
gaitmap_challenges/full_pipeline/__init__.py
gaitmap_challenges/full_pipeline/_utils.py
gaitmap_challenges/full_pipeline/kluge_2017.py
gaitmap_challenges/full_pipeline/sensor_position_comparison_instep.py
gaitmap_challenges/results.py
gaitmap_challenges/spatial_parameters/__init__.py
gaitmap_challenges/spatial_parameters/_utils.py
gaitmap_challenges/spatial_parameters/egait_adidas_2014.py
gaitmap_challenges/spatial_parameters/egait_parameter_validation_2013.py
gaitmap_challenges/spatial_parameters/sensor_position_comparison_instep.py
gaitmap_challenges/stride_segmentation/__init__.py
gaitmap_challenges/stride_segmentation/_utils.py
gaitmap_challenges/stride_segmentation/egait_segmentation_validation_2014.py
gaitmap_challenges/stride_segmentation/egait_segmentation_validation_2014_original_label.py
gaitmap_challenges/stride_segmentation/sensor_position_comparison_instep.py
gaitmap_challenges/visualization/__init__.py
gaitmap_challenges/visualization/_box_plot.py
gaitmap_challenges/visualization/_residual_plot.py
gaitmap_challenges/visualization/_utils.py
gaitmap_challenges-0.1.0.dist-info/METADATA
gaitmap_challenges-0.1.0.dist-info/WHEEL
gaitmap_challenges-0.1.0.dist-info/RECORD
